aqvisa/__init__.py
aqvisa/apptype.py
aqvisa/aqvisalibrary.py
aqvisa/status_code.py
aqvisa/utils/__init__.py
aqvisa/utils/ctypes_wrapper.py
aqvisa/utils/library_wrapper.py
aqvisa-0.0.3.dist-info/licenses/LICENSE
aqvisa-0.0.3.dist-info/METADATA
aqvisa-0.0.3.dist-info/WHEEL
aqvisa-0.0.3.dist-info/top_level.txt
aqvisa-0.0.3.dist-info/RECORD
