Metadata-Version: 2.4
Name: aqvisa
Version: 0.0.3
Summary: Acute VISA Library
Author-email: "Acute Technology Inc." <sdk@acute.com.tw>, Eric Tsai <erictsai@acute.com.tw>
License: BSD 2-Clause License
Project-URL: Homepage, https://github.com/acute-technology-inc/aqvisa-python
Classifier: Development Status :: 4 - Beta
Classifier: Topic :: Software Development
Classifier: License :: OSI Approved :: BSD License
Classifier: Intended Audience :: Developers
Classifier: Operating System :: OS Independent
Classifier: Programming Language :: Python :: 3
Classifier: Programming Language :: Python :: 3.8
Classifier: Programming Language :: Python :: 3.9
Classifier: Programming Language :: Python :: 3.10
Classifier: Programming Language :: Python :: 3.11
Classifier: Programming Language :: Python :: 3.12
Classifier: Programming Language :: Python :: 3.13
Requires-Python: >=3.8
License-File: LICENSE
Dynamic: license-file
